{
  "$schema": "https://mintlify.com/docs.json",
  "theme": "mint",
  "name": "Apex Automation",
  "colors": {
    "primary": "#658a95",
    "light": "#95b6bd",
    "dark": "#4a6b75"
  },
  "favicon": "/favicon.png",
  "logo": {
    "light": "/favicon.png",
    "dark": "/favicon.png"
  },
  "navbar": {
    "links": [
      {
        "label": "Support Server",
        "href": "https://discord.gg/apexautomation"
      }
    ],
    "primary": {
      "type": "button",
      "label": "Home",
      "href": "https://apexautomation.app"
    }
  },
  "navigation": {
    "groups": [
      {
        "group": "Get Started",
        "pages": [
          "get-started/introduction",
          "get-started/system-requirements"
        ]
      },
      {
        "group": "Configuration",
        "pages": [
          "configuration/game-shortcut",
          "configuration/in-game-settings",
          "configuration/bot-configuration"
        ]
      },
      {
        "group": "Efficiency",
        "pages": [
          "efficiency/xp-farming"
        ]
      },
      {
        "group": "Advanced Usage",
        "pages": [
          "advanced/shadow-pc"
        ]
      }
    ],
    "global": {
      "anchors": [
      ]
    }
  },
  "appearance": {
    "default": "dark",
    "strict": true
  },
  "seo": {
    "metatags": {
      "theme-color": "#658a95",
      "og:site_name": "apexautomation.app",
      "title": "Apex Automation Docs",
      "description": "The official documentation for Apex Automation, the ultimate Call of Duty XP farming bot.",
      "keywords": "apex automation, call of duty, xp farming, bot, automation"
    }
  },
  "footer": {
    "socials": {
      "discord": "https://discord.gg/apexautomation"
    }
  },
  "feedback": {
    "enabled": true,
    "thumbsRating": true,
    "suggestEdit": true
  },
  "search": {
    "enabled": true
  }
}
